LbDevTools/Indexing.py
LbDevTools/ProjectDev.py
LbDevTools/ProjectInit.py
LbDevTools/ReleaseNotes.py
LbDevTools/SourceTools.py
LbDevTools/__init__.py
LbDevTools/GitTools/__init__.py
LbDevTools/GitTools/checkout.py
LbDevTools/GitTools/clone_pkg.py
LbDevTools/GitTools/common.py
LbDevTools/GitTools/push.py
LbDevTools/GitTools/reset_mtime.py
LbDevTools/GitTools/use.py
LbDevTools/data/Makefile-cmake.mk
LbDevTools/data/Makefile-cmt-common.mk
LbDevTools/data/Makefile-cmt.mk
LbDevTools/data/Makefile-common.mk
LbDevTools/data/default.clang-format
LbDevTools/data/toolchain.cmake
LbDevTools/data/cmake/BinaryTagUtils.cmake
LbDevTools/data/cmake/CMakeFunctionalUtils.cmake
LbDevTools/data/cmake/CTestXML2HTML
LbDevTools/data/cmake/GangaTools.cmake
LbDevTools/data/cmake/GaudiBuildFlags.cmake
LbDevTools/data/cmake/GaudiCPackSettings.cmake
LbDevTools/data/cmake/GaudiDefaultToolchain.cmake
LbDevTools/data/cmake/GaudiProjectConfig.cmake
LbDevTools/data/cmake/GaudiToolchainMacros.cmake
LbDevTools/data/cmake/HEPToolsMacros.cmake
LbDevTools/data/cmake/InheritHEPTools.cmake
LbDevTools/data/cmake/Instrument.cmake
LbDevTools/data/cmake/LHCbFindPackage.cmake
LbDevTools/data/cmake/LegacyGaudiCMakeSupport.cmake
LbDevTools/data/cmake/README.md
LbDevTools/data/cmake/UseHEPTools.cmake
LbDevTools/data/cmake/cmakeLogToCacheGrind.py
LbDevTools/data/cmake/cpack_install.cmake
LbDevTools/data/cmake/externals.cmake
LbDevTools/data/cmake/extract_qmtest_metadata.py
LbDevTools/data/cmake/gaudi-clang-format-8
LbDevTools/data/cmake/get_host_binary_tag.py
LbDevTools/data/cmake/instrument_func.cmake.in
LbDevTools/data/cmake/quick-merge
LbDevTools/data/cmake/HTMLTestReportSkel/index.html
LbDevTools/data/cmake/HTMLTestReportSkel/css/jquery-ui-1.10.3.css
LbDevTools/data/cmake/HTMLTestReportSkel/css/style.css
LbDevTools/data/cmake/HTMLTestReportSkel/images/ajax-loader.gif
LbDevTools/data/cmake/HTMLTestReportSkel/images/link.png
LbDevTools/data/cmake/HTMLTestReportSkel/images/menu.png
lbdevtools-2.1.6.dist-info/licenses/COPYING
lbdevtools-2.1.6.dist-info/METADATA
lbdevtools-2.1.6.dist-info/WHEEL
lbdevtools-2.1.6.dist-info/entry_points.txt
lbdevtools-2.1.6.dist-info/top_level.txt
lbdevtools-2.1.6.dist-info/RECORD
