Metadata-Version: 2.4
Name: LbDevTools
Version: 2.1.6
Summary: LHCb development tools
Author-email: CERN - LHCb Core Software <lhcb-core-soft@cern.ch>
License: GPLv3+
Project-URL: Homepage, https://gitlab.cern.ch/lhcb-core/LbDevTools
Classifier: Development Status :: 4 - Beta
Classifier: Intended Audience :: Developers
Classifier: Topic :: Software Development :: Build Tools
Classifier: License :: OSI Approved :: GNU General Public License v3 or later (GPLv3+)
Classifier: Programming Language :: Python :: 3
Requires-Python: >=3.12
License-File: COPYING
Requires-Dist: LbEnv>=0.3.0
Requires-Dist: LbPlatformUtils
Requires-Dist: jinja2
Requires-Dist: yapf==0.24.0
Requires-Dist: whichcraft
Requires-Dist: six
Requires-Dist: GitPython>=2.1.12
Requires-Dist: python-gitlab>=2
Requires-Dist: gitdb2>=3
Provides-Extra: testing
Requires-Dist: coverage; extra == "testing"
Requires-Dist: pytest; extra == "testing"
Dynamic: license-file
